smyoon/__init__.py
smyoon/sense/__init__.py
smyoon/sense/_event_client.py
smyoon/sense/_event_result.py
smyoon/sense/config.py
smyoon/sense/exceptions.py
smyoon/sense/file_client.py
smyoon/sense/file_result.py
smyoon/sense/requirements.txt
smyoon/sense/speaker_client.py
smyoon/sense/speaker_result.py
smyoon/sense/stream_client.py
smyoon/sense/version.py
smyoon/sense/window_result.py
smyoon-1.0.2.dist-info/METADATA
smyoon-1.0.2.dist-info/WHEEL
smyoon-1.0.2.dist-info/licenses/LICENSE
smyoon-1.0.2.dist-info/RECORD
