Metadata-Version: 2.3
Name: smyoon
Version: 1.0.2
Summary: Smyoon Sense
Project-URL: Homepage, https://github.com/smyoonlearai/smyoon-sense-py
Project-URL: Issues, https://github.com/smyoonearai/smyoon-sense-py/issues
Author-email: Smyoon <support@smyoon.ai>
License-File: LICENSE
Classifier: License :: OSI Approved :: MIT License
Classifier: Operating System :: OS Independent
Classifier: Programming Language :: Python :: 3
Requires-Python: >=3.8
Requires-Dist: cochl-sense-api==1.6.0
Requires-Dist: requests
Requires-Dist: soundfile
